ml_manager/__init__.py
ml_manager/manage_runs.py
ml_manager-0.2.0.dist-info/METADATA
ml_manager-0.2.0.dist-info/WHEEL
ml_manager-0.2.0.dist-info/top_level.txt
ml_manager-0.2.0.dist-info/RECORD
