Metadata-Version: 2.1
Name: ml-manager
Version: 0.2.0
Summary: A manager which manages all your ML experiments
Author: Manoj Akondi
Author-email: manojakondi25@gmail.com
Keywords: python,pytorch,Machine Learning,Deep Learning
Classifier: Development Status :: 1 - Planning
Classifier: Intended Audience :: Developers
Classifier: Programming Language :: Python :: 3
Classifier: Operating System :: Unix
Classifier: Operating System :: MacOS :: MacOS X
Classifier: Operating System :: Microsoft :: Windows
Requires-Dist: torch
Requires-Dist: numpy
Requires-Dist: matplotlib
Requires-Dist: pandas
